proyecto1/DATA/probador_data.v

////////////////////////////////////////////////////////////////////////////////////////////////////
//	Universidad de Costa Rica
//	Escuela de Ingeniería Eléctrica
//	IE-0523 Circuitos Digitales 2
//
//	Proyecto 1:  SD Host
//
//	Autores:
//  Andrey Pérez Salazar - B25084
//  Andrés Sánchez López - B26214
//  Ronald Rivera Morales - B25565
//  Daniel Jiménez Villalobos - B13535
//
//  Descripción: Probador de Data
////////////////////////////////////////////////////////////////////////////////////////////////////


module probador_data
  (
    output Clock,
    output SD_clock,
    output Reset,
    output WriteRead,        //Escritura 1, lectura 0
    output [7:0] Blocks,     //Cantidad de bloques por procesar
    output MultipleData,     //Multitrama
    output Timeout_enable,
    output [15:0] Timeout_reg, //Ciclos para un timeout
    output NewData,            //Nueva operación
    output Serial_ready ,       //Capa física lista
    output wire Timeout,
    output Complete,           //Capa física terminó
    //output Ack_in,
    output FIFO_ok,
    output wire Data_transfer_complete,  //Hacia el DMA
    output wire Send,           //Se debe empezar a enviar los datos, hacia capa física
    //output wire Ack_out,
    output wire Idle,                //Para decir a capa física que vaya al estado idle
    output Service,        //Para solicitar servicio
    output [31:0] Data_from_FIFO,
    output wire Data_pin_in,
    output wire Data_pin_out
  );


  reg Data_from_FIFO = 1024;

  reg Clock = 0;
  always #20 Clock = !Clock;         //50 MHz

  reg SD_clock = 0;
  always #40 SD_clock = !SD_clock;   //25 MHz

reg Reset=1;
 initial begin
   # 40  Reset = 0;
   # 4000 $finish;
end

reg WriteRead = 1;
reg Blocks = 1;
reg MultipleData = 0;
reg Timeout_enable = 0;
reg Timeout_reg = 70;

reg NewData = 0;
initial begin
  # 200  NewData = 1;
  # 200  NewData = 0;
  # 4000 $finish;
end

/*reg Serial_ready = 0;
initial begin
  # 400  Serial_ready = 1;
  # 200  Serial_ready = 0;
  # 4000 $finish;
end*/

reg FIFO_ok = 0;
initial begin
  # 600  FIFO_ok = 1;
  # 200  FIFO_ok = 0;
  # 4000 $finish;
end

reg Service = 0;
initial begin
  # 200  Service = 1;
  # 300  Service = 0;
  # 4000 $finish;
end

/*reg Complete = 0;
initial begin
  # 800  Complete = 1;
  # 200  Complete = 0;
  # 4000 $finish;
end

reg Ack_in = 0;
initial begin
  # 1000  Ack_in = 1;
  # 200  Ack_in = 0;
  # 4000 $finish;
end*/

endmodule // probador de data

proyecto1/DATA/data.v

////////////////////////////////////////////////////////////////////////////////////////////////////
//	Universidad de Costa Rica
//	Escuela de Ingeniería Eléctrica
//	IE-0523 Circuitos Digitales 2
//
//	Proyecto 1:  SD Host
//
//	Autores:
//  Andrey Pérez Salazar - B25084
//  Andrés Sánchez López - B26214
//  Ronald Rivera Morales - B25565
//  Daniel Jiménez Villalobos - B13535
//
//  Descripción: El bloque de data se encarga de recibir y enviar datos desde y hacia la SD card.
//  Por lo que se compone de dos partes principales, la primera es el control, el cual se comunica
//  con los registros y el DMA para saber cuando se deben enviar o leer datos. La segunda etapa
//  se encarga de enviar y leer los datos en sí, por lo que se cominuca con el FIFO y además
//  convierte la información de paralela a serial y viceversa, se controlada con la parte anterior.
////////////////////////////////////////////////////////////////////////////////////////////////////

module data_control
  (
    input wire iClock,
    input wire iReset,
    input wire iWriteRead,        //Escritura 1, lectura 0
    input wire [3:0] iBlocks,     //Cantidad de bloques por procesar
    input wire iMultipleData,     //Multitrama
    input wire iTimeout_enable,
    input wire [15:0] iTimeout_reg, //Ciclos para un timeout
    input wire iNewData,            //Nueva operación
    input wire iSerial_ready ,       //Capa física lista
    input wire iTimeout,
    input wire iComplete,           //Capa física terminó
    input wire iAck,                //Viene de capa fisica
    input wire iFIFO_ok,
    output wire oData_transfer_complete,  //Hacia el DMA
    output wire oSend,               //Se debe empezar a enviar los datos, hacia capa física
    output wire oAck,                    //Se envía a capa física
    output wire [3:0] oBlocks,      //Cantidad de bloques por procesar, para enviar a capa física
    output wire [15:0] oTimeout_val, //Ciclos para un timeout, para enviar a capa física
    output wire oWriteRead,          //Escritura 1, lectura 0
    output wire oMultipleData,       //enviar a capa física
    output wire oIdle                //Para decir a capa física que vaya al estado idle
  );

parameter SIZE = 3;
parameter IDLE = 3'b111, SETTING_OUTPUTS = 3'b110, CHECK_FIFO = 3'b101;
parameter TRANSMIT = 3'b100, ACK = 3'b011;

reg [SIZE-1:0] rState;
reg [SIZE-1:0] rNext_state;
reg rTemp_Idle;
reg rTemp_send;
reg rTemp_Ack;
reg rTemp_Data_Complete;


always @ (posedge iClock)
begin: FSM_control
if (iReset) begin
  rState <= #1 IDLE;
  rTemp_Data_Complete <= 0;
  rTemp_send <= 0;
  rTemp_Ack <= 0;
  //oBlocks <= 0;
  //oTimeout_val <= 0;
  //oWriteRead <= 0;
  //oMultipleData <= 0;
  rTemp_Idle <= 0;
end
else begin
  case (rState)
    IDLE:
          if (~iNewData) begin
              rTemp_Idle <= 1;
              rState <= #1 IDLE;
           end
           else begin
              rState <= #1 SETTING_OUTPUTS;
           end

   SETTING_OUTPUTS:
          if (iSerial_ready) begin
              //oBlocks <= iBlocks;
              //oTimeout_val <= iTimeout_reg;
              //oWriteRead <= iWriteRead;
              //oMultipleData <= iMultipleData;
              rTemp_Idle <= 0;
              rState <= #1 CHECK_FIFO;
          end
          else begin
              //oBlocks <= iBlocks;
              //oTimeout_val <= iTimeout_reg;
              //oWriteRead <= iWriteRead;
              //oMultipleData <= iMultipleData;
              rTemp_Idle <= 0;
              rState <= #1 SETTING_OUTPUTS;
          end

    CHECK_FIFO:
          if (iFIFO_ok) begin
              //oBlocks <= iBlocks;
              //oTimeout_val <= iTimeout_reg;
              //oWriteRead <= iWriteRead;
              //oMultipleData <= iMultipleData;
              rTemp_Idle <= 0;
              rState <= #1 TRANSMIT;
          end
          else begin
              //oBlocks <= iBlocks;
              //oTimeout_val <= iTimeout_reg;
              //oWriteRead <= iWriteRead;
              //oMultipleData <= iMultipleData;
              rTemp_Idle <= 0;
              rState <= #1 CHECK_FIFO;
          end

      TRANSMIT:
          if (~iComplete) begin
              rTemp_send <= 1'b1;
              rState <= #1 TRANSMIT;
          end
          else begin
              rTemp_send <= 0;
              rState <= #1 ACK;
          end

      ACK:
          if (~iAck) begin
              rTemp_Ack <= 1'b1;
              rState <= #1 ACK;
          end

          else begin
                rTemp_Ack <= 0;
                rTemp_Data_Complete <= 1'b1;
                rState <= IDLE;
          end

    default: rState <= #1 IDLE;
  endcase
  end
end

assign oIdle = rTemp_Idle;
assign oSend = rTemp_send;
assign oAck = rTemp_Ack;
assign oData_transfer_complete = rTemp_Data_Complete;

endmodule    //Control de datos

/**************************************************************************************************/

module data_send
(
  input wire iService,        //Para solicitar servicio
  input wire iAck,            //Viene de control
  input wire iIdle,           //Ir al estado idle
  input wire [15:0] iTimeout_reg, //Ciclos para un timeout
  input wire [7:0] iBlocks,     //Cantidad de bloques por procesar
  input wire iWriteRead,        //Escritura 1, lectura 0
  input wire iMultipleData,     //Multitrama
  input wire [31:0] iData_from_FIFO,
  input wire iReset,
  input wire iClock,             //reloj de la PC
  input wire iSD_clock,          //reloj de SD
  input wire iData_pin,          //Para el envío de datos
  output wire oData_pin,         // Para la recepción de datos
  output wire oSerial_ready ,    //Capa física lista, hacia control
  output wire oComplete,         //Se completó la operación, enviar a control
  output wire oAck,              //Va hacía control
  output wire oTimeout_oc,       //Ocurrencia del timeout, hacia control y registros
  output wire oRead_enable,      //lectura del FIFO, Hacía el FIFO
  output wire oWrite_enable,     //escritura del FIFO, Hacía el FIFO
  output wire oPad_enable,
  output wire oRead_reset,
  output wire oComplete_lectura,
  output wire oComplete_escritura,
  output wire [31:0] oData_to_FIFO
);

parameter SIZE = 4;
parameter IDLE = 4'b1111, FIFO_READ = 4'b1110, LOAD_WRITE = 4'b1101, SEND = 4'b1100;
parameter WAIT_RESPONSE = 4'b1011, READ = 4'b1010, READ_FIFO_WRITE = 4'b1001;
parameter READ_WRAPPER_RESET = 4'b1000, WAIT_ACK = 4'b0111, SEND_ACK = 4'b0110;

reg [SIZE-1:0] rState;
reg [SIZE-1:0] rNext_state;
reg rTemp_Serial_ready, rTemp_Complete, rTemp_oAck;
reg rTemp_Read_enable, rTemp_Write_enable;
reg [31:0] rTemp_Data_from_fifo;
reg rTemp_enable_pad, TEMP, rRead_reset;
reg rComplete_Escritura, rComplete_Lectura;

integer Contador=0;


pad pad_probando
(
  .iOut_in(iWriteRead),
  .iEnable(oPad_enable),
  .iData(iData_pin),
  .iSD_clock(iSD_clock),
  .iIo_port(TEMP),
  .oData(oData_pin)
);

serial_parallel lectura
(
  .iEnable(rTemp_Read_enable),
  .iFrame_size(iBlocks),
  .iSerial(oData_pin),
  .iReset(oRead_reset),
  .iSD_clock(iSD_clock),
  .oParallel(oData_to_FIFO),
  .oComplete(oComplete_lectura)
);

parallel_serial escritura
(
  .iEnable(oWrite_enable),
  .iFrame_size(iBlocks),
  .iReset(iReset),
  .iSD_clock(iSD_clock),
  .iParallel(iData_from_FIFO),
  .oSerial(iData_pin),
  .oComplete(oComplete_escritura)
);


always @ (posedge iSD_clock)
begin: FSM_fisica
  if (iReset) begin
    rState <= #1 IDLE;
    rTemp_Serial_ready <= 0;
    rTemp_Complete <= 0;
    rTemp_oAck <= 0;
    rTemp_Read_enable <= 0;
    rTemp_Write_enable <= 0;
    rRead_reset <= 1'b0;
    //rTemp_enable_pad <= 0;
  end
  else begin
    case (rState)
       IDLE: begin
            rTemp_Write_enable <= 0;
            rTemp_Serial_ready <= 1'b1;
            if (~iService) begin
              rState <= #1 IDLE;
            end
            else begin
              if (iWriteRead) begin
                rState <= #1 LOAD_WRITE;    //Escritura a la SD
              end
              else begin
                rState <= #1 READ;        //Lectura de la SD
              end
            end
          end

      /*  FIFO_READ:
            rTemp_enable_pad <= 1'b1;   //Aquí va sincronización con FIFO
            rState <= #1 LOAD_WRITE;*/

        LOAD_WRITE:
            if (rTemp_enable_pad) begin
              rState <= #1 SEND;
            end
            else begin
              rState <= #1 LOAD_WRITE;
              rTemp_enable_pad <= 1'b1;
            end

        SEND: begin
              rTemp_Write_enable <= 1'b1;
              rState <= #1 WAIT_RESPONSE;
        end

        WAIT_RESPONSE:
         begin
            if (~oComplete_escritura) begin
              rState <= #1 WAIT_RESPONSE;
            end
            else begin
            rTemp_Write_enable <= 0;
            Contador <= Contador + 1;
            if (Contador >= iBlocks) begin
              rState <= #1 WAIT_ACK;
            end
            else begin
              rState <= #1 LOAD_WRITE;
              end
            end // -,-
          end

        READ: begin
            if (~oComplete_lectura) begin
              rRead_reset <= 0;
              rTemp_enable_pad <= 1'b0;
              rTemp_Read_enable <= 1'b1;
              rState <= #1 READ;
            end else begin
              rRead_reset <= 1'b0;
              Contador <= Contador + 1;
              if (Contador >= iBlocks) begin
                  rState <= #1 WAIT_ACK;
              end
              else begin
                  rState <= #1 READ_WRAPPER_RESET;
              end
            end
          end

          //READ_FIFO_WRITE -> Sync con FIFO

          READ_WRAPPER_RESET: begin
            rRead_reset <= 1'b1;
            rState <= #1 READ;
          end

          WAIT_ACK: begin
            rTemp_Complete <= 1'b1;
            if (iAck) begin
              rState <= #1 SEND_ACK;
            end
            else begin
              rState <= #1 WAIT_ACK;
            end
          end

          SEND_ACK: begin
              rTemp_oAck <= 1'b1;
              rState <= #1 IDLE;
          end


       default: rState <= #1 IDLE;
    endcase
  end
end

assign oSerial_ready = rTemp_Serial_ready;
assign oComplete = rTemp_Complete;
assign oAck = rTemp_oAck;
assign oRead_enable = rTemp_Read_enable;
assign oWrite_enable = rTemp_Write_enable;
assign oPad_enable = rTemp_enable_pad;
assign oRead_reset = rRead_reset;
//assign oData_to_FIFO = rTemp_Data_to_fifo;

endmodule // Envío de los datos

/**************************************************************************************************/

module serial_parallel
(
  input wire iEnable,
  input wire [7:0] iFrame_size,  //Tamaño de trama
  input wire iSerial,
  //input wire [3:0] iSerial_multi,
  input wire iReset,
  input wire iSD_clock,
  output wire [31:0] oParallel,
  output wire oComplete         //Este complete es distinto al general de la capa de datos
);

reg [31:0] rA;  //Para guardar resultados en paralelo
reg rB;         //Para guardar oComplete

//Para Trama:
  integer i;
  always @ (posedge iSD_clock & iEnable) begin
    if (~iReset) begin
      for (i=0; i <= 31; i = i + 1) begin
          rA[i] <= iSerial;
          if (i>=31) begin
              rB <= 1;
          end
          else begin
              rB <= 0;
          end
      end
    end
    else begin
      rA <= 0;
    end
  end

  assign oParallel = rA;
  assign oComplete = rB;


//Para Multitrama:
/*integer i;
always @ (posedge iSD_clock && iEnable) begin
  if (~iReset) begin
    for (i=0; i <= 7; i = i + 1) begin
        rA[(i*4)+:3] <= iSerial_multi;
        if (i>=7) begin
            rB <= 1;
        end
        else begin
            rB <= 0;
        end
    end
  end
  else begin
    rA = 0;
  end
end

assign oParallel = rA;
assign oComplete = rB;*/


endmodule //Para pasar info de serial a paralelo

/**************************************************************************************************/

module parallel_serial
(
  input wire iEnable,
  input wire [7:0] iFrame_size,  //Tamaño de trama
  input wire iReset,
  input wire iSD_clock,
  input wire [31:0] iParallel,
  output wire oSerial,
  output wire [3:0] oSerial_multi,
  output wire oComplete
);

reg rC;  //Para guardar resultados Seriales
reg [3:0] rE;  //Para Multitrama
reg rD;  //Para guardar oComplete

//Para trama:
integer j=0;
always @ (posedge iSD_clock && iEnable==1) begin
  if (~iReset) begin
      rC <= iParallel[j];
      j = j + 1;
      if (j>=32) begin
          rD <= 1;
      end
      else begin
          rD <= 0;
      end
  end
  else begin
    rC <= 0;
    rD <= 0;
  end
end

assign oSerial = rC;
assign oComplete = rD;

//Para Multitrama:
/*integer j;
always @ (posedge iSD_clock) begin
  if (~iReset) begin
  for (j=0; j <= 7; j = j + 1) begin
      rE <= iParallel[j*4+:3];
      if (j>=7) begin
          rD <= 1;
      end
      else begin
          rD <= 0;
      end
  end
  end
  else begin
    rE <= 0;
  end
end

assign oSerial_multi = rE;
assign oComplete = rD;*/

endmodule // Para pasar info de paralelo a serial

/**************************************************************************************************/

module pad
(
    input wire iOut_in,       //1 Esritura, 0 Lectura
    input wire iEnable,
    input wire iData,        //Dato de entrada si se Escribe a la tarjeta
    input wire iSD_clock,
    input wire iIo_port,     //PIN de salida del SD_HOST, lo que va a la tarjeta
    output wire oData       //Dato de salida si se lee de la tarjeta
);

reg      a;
reg      b;

assign iIo_port = iOut_in ? a : 1'bZ ;
assign oData  = b;

always @ (posedge iSD_clock && iEnable)
begin
    b <= iIo_port;
    a <= iData;
end


endmodule // pad de datos

/**************************************************************************************************/

proyecto1/DATA/data_tb.v

////////////////////////////////////////////////////////////////////////////////////////////////////
//	Universidad de Costa Rica
//	Escuela de Ingeniería Eléctrica
//	IE-0523 Circuitos Digitales 2
//
//	Proyecto 1:  SD Host
//
//	Autores:
//  Andrey Pérez Salazar - B25084
//  Andrés Sánchez López - B26214
//  Ronald Rivera Morales - B25565
//  Daniel Jiménez Villalobos - B13535
//
//  Descripción: Este es el test bench de Data
////////////////////////////////////////////////////////////////////////////////////////////////////

`timescale 1ns/1ps

module test_data;

initial begin
  $dumpfile("probador_data.vcd");
  $dumpvars(0,test_data);
end

parameter FIFO_data_size = 32;
parameter Blocks_size_to_process = 8;
parameter Register_size = 16;


wire Clock, Reset, WriteRead, MultipleData, Timeout_enable, NewData, Serial_ready, Timeout;
wire Complete, Ack_in_control, FIFO_ok, Data_transfer_complete, Send, Ack_in_phys, Idle;
wire Service, SD_clock, Data_pin_in, Data_pin_out, Timeout_oc, Read_enable, TEMP;
wire Write_enable, Complete_lectura, Complete_escritura;
wire [Blocks_size_to_process-1:0] Blocks;
wire [Register_size-1:0] Timeout_reg;
wire [FIFO_data_size-1:0] Data_from_FIFO, Data_to_FIFO;

data_control Control_datos
  (
    .iClock(Clock),
    .iReset(Reset),
    .iWriteRead(WriteRead),
    .iBlocks(Blocks),
    .iMultipleData(MultipleData),
    .iTimeout_enable(Timeout_enable),
    .iTimeout_reg(Timeout_reg),
    .iNewData(NewData),
    .iSerial_ready(Serial_ready),
    .iTimeout(Timeout),
    .iComplete(Complete),
    .iAck(Ack_in_control),
    .iFIFO_ok(FIFO_ok),
    .oData_transfer_complete(Data_transfer_complete),
    .oSend(Send),
    .oAck(Ack_in_phys),
    .oBlocks(Blocks),
    .oTimeout_val(Timeout_reg),
    .oWriteRead(WriteRead),
    .oMultipleData(MultipleData),
    .oIdle(Idle)
  );

  data_send Capa_Fisica_datos
  (
    .iService(Service),
    .iAck(Ack_in_phys),
    .iIdle(Idle),
    .iTimeout_reg(Timeout_reg),
    .iBlocks(Blocks),
    .iWriteRead(WriteRead),
    .iMultipleData(MultipleData),
    .iData_from_FIFO(Data_from_FIFO),
    .iReset(Reset),
    .iClock(Clock),
    .iSD_clock(SD_clock),
    .iData_pin(Data_pin_in),
    .oData_pin(Data_pin_out),
    .oSerial_ready(Serial_ready),
    .oComplete(Complete),
    .oAck(Ack_in_control),
    .oTimeout_oc(Timeout_oc),
    .oRead_enable(Read_enable),
    .oWrite_enable(Write_enable),
    .oComplete_lectura(Complete_lectura),
    .oComplete_escritura(Complete_escritura),
    .oData_to_FIFO(Data_to_FIFO)
  );

  probador_data probador
    (
      .Clock(Clock),
      .SD_clock(SD_clock),
      .Reset(Reset),
      .WriteRead(WriteRead),
      .Blocks(Blocks),
      .MultipleData(MultipleData),
      .Timeout_enable(Timeout_enable),
      .Timeout_reg(Timeout_reg),
      .NewData(NewData),
      .Serial_ready(Serial_ready),
      .Timeout(Timeout),
      .Complete(Complete),
      //.Ack_in(Ack_in_control),
      .FIFO_ok(FIFO_ok),
      .Data_transfer_complete(Data_transfer_complete),
      .Send(Send),
      //.Ack_out(Ack_out),
      .Idle(Idle),
      .Service(Service),
      .Data_from_FIFO(Data_from_FIFO),
      .Data_pin_in(Data_pin_in),
      .Data_pin_out(Data_pin_out)
    );




endmodule    //Test bench de data

proyecto1/DATA/probador_data.vcd
$date
	Mon Dec  5 15:48:17 2016
$end
$version
	Icarus Verilog
$end
$timescale
	1ps
$end
$scope module test_data $end
$var wire 1 ! Ack_in_control $end
$var wire 1 " Ack_in_phys $end
$var wire 8 # Blocks [7:0] $end
$var wire 1 $ Clock $end
$var wire 1 % Complete $end
$var wire 1 & Complete_escritura $end
$var wire 1 ' Complete_lectura $end
$var wire 32 ( Data_from_FIFO [31:0] $end
$var wire 1 ) Data_pin_in $end
$var wire 1 * Data_pin_out $end
$var wire 32 + Data_to_FIFO [31:0] $end
$var wire 1 , Data_transfer_complete $end
$var wire 1 - FIFO_ok $end
$var wire 1 . Idle $end
$var wire 1 / MultipleData $end
$var wire 1 0 NewData $end
$var wire 1 1 Read_enable $end
$var wire 1 2 Reset $end
$var wire 1 3 SD_clock $end
$var wire 1 4 Send $end
$var wire 1 5 Serial_ready $end
$var wire 1 6 Service $end
$var wire 1 7 Timeout $end
$var wire 1 8 Timeout_enable $end
$var wire 1 9 Timeout_oc $end
$var wire 16 : Timeout_reg [15:0] $end
$var wire 1 ; WriteRead $end
$var wire 1 < Write_enable $end
$scope module Control_datos $end
$var wire 1 ! iAck $end
$var wire 4 = iBlocks [3:0] $end
$var wire 1 $ iClock $end
$var wire 1 % iComplete $end
$var wire 1 - iFIFO_ok $end
$var wire 1 / iMultipleData $end
$var wire 1 0 iNewData $end
$var wire 1 2 iReset $end
$var wire 1 5 iSerial_ready $end
$var wire 1 7 iTimeout $end
$var wire 1 8 iTimeout_enable $end
$var wire 16 > iTimeout_reg [15:0] $end
$var wire 1 ; iWriteRead $end
$var wire 1 " oAck $end
$var wire 4 ? oBlocks [3:0] $end
$var wire 1 , oData_transfer_complete $end
$var wire 1 . oIdle $end
$var wire 1 / oMultipleData $end
$var wire 1 4 oSend $end
$var wire 16 @ oTimeout_val [15:0] $end
$var wire 1 ; oWriteRead $end
$var reg 3 A rState [2:0] $end
$var reg 1 B rTemp_Ack $end
$var reg 1 C rTemp_Data_Complete $end
$var reg 1 D rTemp_Idle $end
$var reg 1 E rTemp_send $end
$scope begin FSM_control $end
$upscope $end
$upscope $end
$scope module Capa_Fisica_datos $end
$var wire 1 " iAck $end
$var wire 8 F iBlocks [7:0] $end
$var wire 1 $ iClock $end
$var wire 32 G iData_from_FIFO [31:0] $end
$var wire 1 ) iData_pin $end
$var wire 1 . iIdle $end
$var wire 1 / iMultipleData $end
$var wire 1 2 iReset $end
$var wire 1 3 iSD_clock $end
$var wire 1 6 iService $end
$var wire 16 H iTimeout_reg [15:0] $end
$var wire 1 ; iWriteRead $end
$var wire 1 ! oAck $end
$var wire 1 % oComplete $end
$var wire 1 & oComplete_escritura $end
$var wire 1 ' oComplete_lectura $end
$var wire 1 * oData_pin $end
$var wire 32 I oData_to_FIFO [31:0] $end
$var wire 1 J oPad_enable $end
$var wire 1 1 oRead_enable $end
$var wire 1 K oRead_reset $end
$var wire 1 5 oSerial_ready $end
$var wire 1 9 oTimeout_oc $end
$var wire 1 < oWrite_enable $end
$var integer 32 L Contador [31:0] $end
$var reg 1 M TEMP $end
$var reg 1 N rRead_reset $end
$var reg 4 O rState [3:0] $end
$var reg 1 P rTemp_Complete $end
$var reg 1 Q rTemp_Read_enable $end
$var reg 1 R rTemp_Serial_ready $end
$var reg 1 S rTemp_Write_enable $end
$var reg 1 T rTemp_enable_pad $end
$var reg 1 U rTemp_oAck $end
$scope module pad_probando $end
$var wire 1 ) iData $end
$var wire 1 J iEnable $end
$var wire 1 V iIo_port $end
$var wire 1 ; iOut_in $end
$var wire 1 3 iSD_clock $end
$var wire 1 * oData $end
$var reg 1 W a $end
$var reg 1 X b $end
$upscope $end
$scope module lectura $end
$var wire 1 Y iEnable $end
$var wire 8 Z iFrame_size [7:0] $end
$var wire 1 K iReset $end
$var wire 1 3 iSD_clock $end
$var wire 1 * iSerial $end
$var wire 1 ' oComplete $end
$var wire 32 [ oParallel [31:0] $end
$var integer 32 \ i [31:0] $end
$var reg 32 ] rA [31:0] $end
$var reg 1 ^ rB $end
$upscope $end
$scope module escritura $end
$var wire 1 < iEnable $end
$var wire 8 _ iFrame_size [7:0] $end
$var wire 32 ` iParallel [31:0] $end
$var wire 1 2 iReset $end
$var wire 1 3 iSD_clock $end
$var wire 1 & oComplete $end
$var wire 1 ) oSerial $end
$var wire 4 a oSerial_multi [3:0] $end
$var integer 32 b j [31:0] $end
$var reg 1 c rC $end
$var reg 1 d rD $end
$upscope $end
$scope begin FSM_fisica $end
$upscope $end
$upscope $end
$scope module probador $end
$var wire 1 % Complete $end
$var wire 1 ) Data_pin_in $end
$var wire 1 * Data_pin_out $end
$var wire 1 , Data_transfer_complete $end
$var wire 1 . Idle $end
$var wire 1 4 Send $end
$var wire 1 5 Serial_ready $end
$var wire 1 7 Timeout $end
$var reg 8 e Blocks [7:0] $end
$var reg 1 f Clock $end
$var reg 32 g Data_from_FIFO [31:0] $end
$var reg 1 h FIFO_ok $end
$var reg 1 i MultipleData $end
$var reg 1 j NewData $end
$var reg 1 k Reset $end
$var reg 1 l SD_clock $end
$var reg 1 m Service $end
$var reg 1 n Timeout_enable $end
$var reg 16 o Timeout_reg [15:0] $end
$var reg 1 p WriteRead $end
$upscope $end
$upscope $end
$enddefinitions $end
#0
$dumpvars
1p
b1000110 o
0n
0m
0l
1k
0j
0i
0h
b10000000000 g
0f
b1 e
xd
xc
b0 b
bz a
b10000000000 `
b1 _
x^
bx ]
bx \
bx [
b1 Z
xY
xX
xW
xV
xU
xT
xS
xR
xQ
xP
bx O
xN
xM
b0 L
xK
xJ
bx I
b1000110 H
b10000000000 G
b1 F
xE
xD
xC
xB
bx A
b1000110 @
bz ?
b1000110 >
b1 =
x<
1;
b1000110 :
z9
08
z7
06
x5
x4
03
12
x1
00
0/
x.
0-
x,
bx +
x*
x)
b10000000000 (
x'
x&
x%
0$
b1 #
x"
x!
$end
#20000
0D
0.
0B
0"
0E
04
0C
0,
1f
1$
#21000
b111 A
#40000
0d
0&
0c
0)
b0 ]
b0 +
b0 I
b0 [
b1 b
0f
0$
0k
02
1l
13
#41000
b1111 O
#60000
1D
1.
1f
1$
#80000
0f
0$
0l
03
#100000
1f
1$
#120000
0W
1R
15
0S
0<
b10 b
0f
0$
1l
13
#140000
1f
1$
#160000
0f
0$
0l
03
#180000
1f
1$
#200000
0f
0$
1l
13
1m
16
1j
10
#201000
b1101 O
#220000
1f
1$
#221000
b110 A
#240000
0f
0$
0l
03
#260000
0D
0.
1f
1$
#261000
b101 A
#280000
1T
1J
0f
0$
1l
13
#300000
1f
1$
#320000
0f
0$
0l
03
#340000
1f
1$
#360000
0f
0$
1l
13
#361000
b1100 O
#380000
1f
1$
#400000
0f
0$
0l
03
0j
00
#420000
1f
1$
#440000
b11 b
1S
1<
0f
0$
1l
13
#441000
b1011 O
#460000
1f
1$
#480000
0f
0$
0l
03
#500000
1f
1$
0m
06
#520000
b100 b
0f
0$
1l
13
#540000
1f
1$
#560000
0f
0$
0l
03
#580000
1f
1$
#600000
b101 b
0f
0$
1l
13
1h
1-
#620000
1f
1$
#621000
b100 A
#640000
0f
0$
0l
03
#660000
1f
1$
#661000
b11 A
#680000
b110 b
0f
0$
1l
13
#700000
b111 A
1C
1,
1f
1$
#720000
0f
0$
0l
03
#740000
1D
1.
1f
1$
#760000
b111 b
0f
0$
1l
13
#780000
1f
1$
#800000
0f
0$
0l
03
0h
0-
#820000
1f
1$
#840000
b1000 b
0f
0$
1l
13
#860000
1f
1$
#880000
0f
0$
0l
03
#900000
1f
1$
#920000
b1001 b
0f
0$
1l
13
#940000
1f
1$
#960000
0f
0$
0l
03
#980000
1f
1$
#1000000
b1010 b
0f
0$
1l
13
#1020000
1f
1$
#1040000
0f
0$
0l
03
#1060000
1f
1$
#1080000
1c
1)
b1011 b
0f
0$
1l
13
#1100000
1f
1$
#1120000
0f
0$
0l
03
#1140000
1f
1$
#1160000
0c
0)
1W
b1100 b
0f
0$
1l
13
#1180000
1f
1$
#1200000
0f
0$
0l
03
#1220000
1f
1$
#1240000
0W
b1101 b
0f
0$
1l
13
#1260000
1f
1$
#1280000
0f
0$
0l
03
#1300000
1f
1$
#1320000
b1110 b
0f
0$
1l
13
#1340000
1f
1$
#1360000
0f
0$
0l
03
#1380000
1f
1$
#1400000
b1111 b
0f
0$
1l
13
#1420000
1f
1$
#1440000
0f
0$
0l
03
#1460000
1f
1$
#1480000
b10000 b
0f
0$
1l
13
#1500000
1f
1$
#1520000
0f
0$
0l
03
#1540000
1f
1$
#1560000
b10001 b
0f
0$
1l
13
#1580000
1f
1$
#1600000
0f
0$
0l
03
#1620000
1f
1$
#1640000
b10010 b
0f
0$
1l
13
#1660000
1f
1$
#1680000
0f
0$
0l
03
#1700000
1f
1$
#1720000
b10011 b
0f
0$
1l
13
#1740000
1f
1$
#1760000
0f
0$
0l
03
#1780000
1f
1$
#1800000
b10100 b
0f
0$
1l
13
#1820000
1f
1$
#1840000
0f
0$
0l
03
#1860000
1f
1$
#1880000
b10101 b
0f
0$
1l
13
#1900000
1f
1$
#1920000
0f
0$
0l
03
#1940000
1f
1$
#1960000
b10110 b
0f
0$
1l
13
#1980000
1f
1$
#2000000
0f
0$
0l
03
#2020000
1f
1$
#2040000
b10111 b
0f
0$
1l
13
#2060000
1f
1$
#2080000
0f
0$
0l
03
#2100000
1f
1$
#2120000
b11000 b
0f
0$
1l
13
#2140000
1f
1$
#2160000
0f
0$
0l
03
#2180000
1f
1$
#2200000
b11001 b
0f
0$
1l
13
#2220000
1f
1$
#2240000
0f
0$
0l
03
#2260000
1f
1$
#2280000
b11010 b
0f
0$
1l
13
#2300000
1f
1$
#2320000
0f
0$
0l
03
#2340000
1f
1$
#2360000
b11011 b
0f
0$
1l
13
#2380000
1f
1$
#2400000
0f
0$
0l
03
#2420000
1f
1$
#2440000
b11100 b
0f
0$
1l
13
#2460000
1f
1$
#2480000
0f
0$
0l
03
#2500000
1f
1$
#2520000
b11101 b
0f
0$
1l
13
#2540000
1f
1$
#2560000
0f
0$
0l
03
#2580000
1f
1$
#2600000
b11110 b
0f
0$
1l
13
#2620000
1f
1$
#2640000
0f
0$
0l
03
#2660000
1f
1$
#2680000
b11111 b
0f
0$
1l
13
#2700000
1f
1$
#2720000
0f
0$
0l
03
#2740000
1f
1$
#2760000
1d
1&
b100000 b
0f
0$
1l
13
#2780000
1f
1$
#2800000
0f
0$
0l
03
#2820000
1f
1$
#2840000
xc
x)
b1 L
0S
0<
b100001 b
0f
0$
1l
13
#2841000
b1101 O
#2860000
1f
1$
#2880000
0f
0$
0l
03
#2900000
1f
1$
#2920000
xW
0f
0$
1l
13
#2921000
b1100 O
#2940000
1f
1$
#2960000
0f
0$
0l
03
#2980000
1f
1$
#3000000
b100010 b
1S
1<
0f
0$
1l
13
#3001000
b1011 O
#3020000
1f
1$
#3040000
0f
0$
0l
03
#3060000
1f
1$
#3080000
b10 L
0S
0<
b100011 b
0f
0$
1l
13
#3081000
b111 O
#3100000
1f
1$
#3120000
0f
0$
0l
03
#3140000
1f
1$
#3160000
1P
1%
0f
0$
1l
13
